sevq/__init__.py
sevq/algorithm.py
sevq-1.0.2.dist-info/AUTHORS.rst
sevq-1.0.2.dist-info/LICENSE
sevq-1.0.2.dist-info/METADATA
sevq-1.0.2.dist-info/WHEEL
sevq-1.0.2.dist-info/top_level.txt
sevq-1.0.2.dist-info/RECORD
