Metadata-Version: 2.1
Name: sevq
Version: 1.0.2
Summary: SEVQ: Simple Evolving Vector Quantization
Home-page: https://github.com/sylwekczmil/sevq
Author: Sylwester Czmil
Author-email: sylwekczmil@gmail.com
License: MIT license
Keywords: sevq
Platform: UNKNOWN
Classifier: Development Status :: 2 - Pre-Alpha
Classifier: Intended Audience :: Developers
Classifier: License :: OSI Approved :: MIT License
Classifier: Natural Language :: English
Classifier: Programming Language :: Python :: 3
Classifier: Programming Language :: Python :: 3.6
Classifier: Programming Language :: Python :: 3.7
Classifier: Programming Language :: Python :: 3.8
Requires-Python: >=3.6
Requires-Dist: numpy (>=1.18.5)
